qqman/__init__.py
qqman/biostats.py
qqman/qqman.py
qqman-1.0.8.dist-info/METADATA
qqman-1.0.8.dist-info/WHEEL
qqman-1.0.8.dist-info/licenses/LICENSE
qqman-1.0.8.dist-info/RECORD
