Metadata-Version: 2.4
Name: qqman
Version: 1.0.8
Summary: Draws Manhattan plot and QQ plot using plink assoc output
Project-URL: Homepage, https://github.com/satchellhong/qqman
Project-URL: Bug Tracker, https://github.com/satchellhong/qqman/issues
Project-URL: Source Code, https://github.com/satchellhong/qqman
Author-email: chol hong <shulkhorn@gmail.com>
Maintainer-email: chol hong <shulkhorn@gmail.com>
License: MIT
License-File: LICENSE
Keywords: bioinformatics,genomics,gwas,manhattan plot,qq plot,visualization
Classifier: Development Status :: 5 - Production/Stable
Classifier: Intended Audience :: Science/Research
Classifier: License :: OSI Approved :: MIT License
Classifier: Operating System :: OS Independent
Classifier: Programming Language :: Python :: 3
Classifier: Programming Language :: Python :: 3.10
Classifier: Programming Language :: Python :: 3.11
Classifier: Programming Language :: Python :: 3.12
Classifier: Topic :: Scientific/Engineering :: Bio-Informatics
Classifier: Topic :: Scientific/Engineering :: Visualization
Requires-Python: >=3.10
Requires-Dist: matplotlib<4.0.0,>=3.7.0
Requires-Dist: numpy<3.0.0,>=1.23.5
Requires-Dist: pandas<3.0.0,>=1.5.3
Provides-Extra: dev
Requires-Dist: pytest-cov>=4.0.0; extra == 'dev'
Requires-Dist: pytest>=7.0.0; extra == 'dev'
Requires-Dist: ruff>=0.4.8; extra == 'dev'
